ayed/__main__.py
ayed/classes.py
ayed/editor.py
ayed/excel.py
ayed/exceptions.py
ayed/parser.py
ayed/printer.py
ayed/tool.py
ayed/types.py
ayed/utils.py
ayed-1.1.0.dist-info/entry_points.txt
ayed-1.1.0.dist-info/LICENSE
ayed-1.1.0.dist-info/WHEEL
ayed-1.1.0.dist-info/METADATA
ayed-1.1.0.dist-info/RECORD
