Metadata-Version: 2.1
Name: ayed
Version: 1.1.0
Summary: AyED Tools
Home-page: https://github.com/Bocanada/AyED-Tool
License: MIT
Author: Bocanada
Author-email: 24578415+Bocanada@users.noreply.github.com
Requires-Python: >=3.9,<4.0
Classifier: License :: OSI Approved :: MIT License
Classifier: Programming Language :: Python :: 3
Classifier: Programming Language :: Python :: 3.9
Requires-Dist: openpyxl (>=3.0.7,<4.0.0)
Requires-Dist: pandas (>=1.2.4,<2.0.0)
Requires-Dist: rich (>=10.4.0,<11.0.0)
Requires-Dist: typer (>=0.3.2,<0.4.0)
Project-URL: Repository, https://github.com/Bocanada/AyED-Tool
